pyjson_translator/__init__.py
pyjson_translator/annotation.py
pyjson_translator/db_sqlalchemy_instance.py
pyjson_translator/error_handle.py
pyjson_translator/logger_setting.py
pyjson_translator/marshmallow_db_util.py
pyjson_translator/pydantic_db_util.py
pyjson_translator/serialize.py
pyjson_translator-0.1.27.dist-info/LICENSE
pyjson_translator-0.1.27.dist-info/METADATA
pyjson_translator-0.1.27.dist-info/WHEEL
pyjson_translator-0.1.27.dist-info/RECORD
